{"gunvfl59nIjGYP894LqYRQ==":"imgen1-2000x699.jpg","c58cAK4ch6KQpCOr1SXGqw==":"imgen1-1-2000x699.jpg","sKdCjsia79gVyqK0BhiZbA==":"logocadcam2-122x81.png","aWFxHaCxDz2mcq5imqYsuw==":"logocadcam2-192x128.png","D4KRPT8ttisXUT7kMATRAA==":"fondo1-2000x1600.jpg","uTZO7JAqJoUl7/wXdZiJGQ==":"designing-the-buccal-of-zirlux-tooth-19-in-dental-wings-1368x770.png","a6aX6RgW7IX1HqmqfAwcgg==":"fondo4-2000x1600.jpg","35J2ABzR9oY83uONTfKRyA==":"fondo5-2000x1600.jpg","va9xO/7UehrG5ULqIGyg6w==":"cad-cam-dental-radiografia-dental-3d-digital%20copy-700x460.jpg"}